generate_dense_patches/__init__.py
generate_dense_patches/_widget.py
generate_dense_patches/napari.yaml
generate_dense_patches/_tests/__init__.py
generate_dense_patches/_tests/test_widget.py
generate_dense_patches-0.0.2.dist-info/LICENSE
generate_dense_patches-0.0.2.dist-info/METADATA
generate_dense_patches-0.0.2.dist-info/WHEEL
generate_dense_patches-0.0.2.dist-info/entry_points.txt
generate_dense_patches-0.0.2.dist-info/top_level.txt
generate_dense_patches-0.0.2.dist-info/RECORD
