Metadata-Version: 2.1
Name: generate-dense-patches
Version: 0.0.2
Summary: A simple plugin to create a lot of training data from a 3D volume and mask
Home-page: https://github.com/volume-em/generate-dense-patches
Author: Aayush Bhatawadekar
Author-email: asbhatawadekar@gmail.com
License: BSD-3-Clause
Project-URL: Bug Tracker, https://github.com/volume-em/generate-dense-patches/issues
Project-URL: Documentation, https://github.com/volume-em/generate-dense-patches#README.md
Project-URL: Source Code, https://github.com/volume-em/generate-dense-patches
Project-URL: User Support, https://github.com/volume-em/generate-dense-patches/issues
Classifier: Development Status :: 2 - Pre-Alpha
Classifier: Framework :: napari
Classifier: Intended Audience :: Developers
Classifier: License :: OSI Approved :: BSD License
Classifier: Operating System :: OS Independent
Classifier: Programming Language :: Python
Classifier: Programming Language :: Python :: 3
Classifier: Programming Language :: Python :: 3 :: Only
Classifier: Programming Language :: Python :: 3.8
Classifier: Programming Language :: Python :: 3.9
Classifier: Programming Language :: Python :: 3.10
Classifier: Topic :: Scientific/Engineering :: Image Processing
Requires-Python: >=3.8
License-File: LICENSE
Requires-Dist: napari >=0.4.18
Requires-Dist: napari-plugin-engine >=0.2.0
Requires-Dist: numpy ==1.22
Requires-Dist: scikit-image >=0.19
Requires-Dist: magicgui
Requires-Dist: imagecodecs
Provides-Extra: testing
Requires-Dist: tox ; extra == 'testing'
Requires-Dist: pytest ; extra == 'testing'
Requires-Dist: pytest-cov ; extra == 'testing'
Requires-Dist: pytest-qt ; extra == 'testing'
Requires-Dist: napari ; extra == 'testing'
Requires-Dist: pyqt5 ; extra == 'testing'
